nonebot_plugin_russian/__init__.py
nonebot_plugin_russian/config.py
nonebot_plugin_russian/data_source.py
nonebot_plugin_russian/utils.py
nonebot_plugin_russian-0.2.5.dist-info/LICENSE
nonebot_plugin_russian-0.2.5.dist-info/WHEEL
nonebot_plugin_russian-0.2.5.dist-info/METADATA
nonebot_plugin_russian-0.2.5.dist-info/RECORD
